src/__init__.py
src/scanerr/__init__.py
src/scanerr/api.py
src/scanerr/root.py
scanerr-0.0.10.dist-info/LICENSE.md
scanerr-0.0.10.dist-info/METADATA
scanerr-0.0.10.dist-info/WHEEL
scanerr-0.0.10.dist-info/entry_points.txt
scanerr-0.0.10.dist-info/top_level.txt
scanerr-0.0.10.dist-info/RECORD
