Metadata-Version: 2.1
Name: scanerr
Version: 0.0.10
Summary: Official Scanerr CLI
Author-email: Scanerr <hello@scanerr.io>
Project-URL: Homepage, https://github.com/scanerr-io/cli
Project-URL: Issues, https://github.com/scanerr-io/cli/issues
Project-URL: Documentaion, https://docs.scanerr.io
Keywords: regression testing,vrt,visual regression testing
Classifier: Programming Language :: Python :: 3
Classifier: License :: OSI Approved :: MIT License
Classifier: Operating System :: OS Independent
Requires-Python: >=3.9
License-File: LICENSE.md
Requires-Dist: python-dotenv
Requires-Dist: requests
Requires-Dist: rich
Requires-Dist: typer
